openstep_plist-0.5.1.dist-info/RECORD
openstep_plist-0.5.1.dist-info/WHEEL
openstep_plist-0.5.1.dist-info/top_level.txt
openstep_plist-0.5.1.dist-info/METADATA
openstep_plist-0.5.1.dist-info/licenses/LICENSE
openstep_plist/util.pxd
openstep_plist/parser.pyx
openstep_plist/writer.pyx
openstep_plist/util.cpython-314t-darwin.so
openstep_plist/_version.py
openstep_plist/__init__.py
openstep_plist/writer.cpython-314t-darwin.so
openstep_plist/_test.pyx
openstep_plist/_test.cpython-314t-darwin.so
openstep_plist/parser.cpython-314t-darwin.so
openstep_plist/writer.pxd
openstep_plist/__main__.py
openstep_plist/parser.pxd
openstep_plist/util.pyx
