Metadata-Version: 2.1
Name: openstep_plist
Version: 0.5.1
Summary: ASCII plist parser written in Cython
Home-page: https://github.com/fonttools/openstep-plist
Author: Cosimo Lupo
Author-email: cosimo@anthrotype.com
License: MIT
Requires-Python: >=3.8
License-File: LICENSE
